{
  "Architecture": [
    "any"
  ],
  "Binary": [
    "netcfg, netcfg-static"
  ],
  "Build-Depends": [
    "debhelper-compat (= 13), libdebconfclient0-dev, libdebian-installer4-dev, po-debconf, libiw-dev [!s390 !s390x !sparc !kfreebsd-any !hurd-any], check, libsubunit-dev"
  ],
  "Checksums-Sha1": [
    "d17018d8de936cafebe36d86bd63b6a3eb3c3ab2 916 netcfg_1.197elxr1.dsc ba50621feed39d4ed1fefc5d11c35f608c987de7 407272 netcfg_1.197elxr1.tar.xz"
  ],
  "Checksums-Sha256": [
    "47df3b1a63f257d70ec9cff7a63a0b16157199f66f2404003a7cfd48d97dcd90 916 netcfg_1.197elxr1.dsc d6dbdeb2aeadb68b0148b5744b59b6fc4515fcf4c2c84558d73fece4e6e5285b 407272 netcfg_1.197elxr1.tar.xz"
  ],
  "Checksums-Sha512": [
    "ef022a3024a2f33ffa5dee292cef52471d90e4c78d337b0792277928a7a814b0fac3594542069f9188e73b56b0718ba5f0abc881f93c6b7725c5b2cd4e576223 916 netcfg_1.197elxr1.dsc a9ecfc70b15b299f2ca77c233831f473262ae2c55047553a682e4dd4f1254fc18e7e498f0ed41ec87830f2401842c6da4e013b12d4f9ab7767a27dd29ca14e2d 407272 netcfg_1.197elxr1.tar.xz"
  ],
  "Directory": [
    "pool/main/n/netcfg"
  ],
  "Files": [
    "e4c51bc98c0710a0a5de959b57a25947 916 netcfg_1.197elxr1.dsc 8252480e4a57f6da54f3c8ac87e52f9c 407272 netcfg_1.197elxr1.tar.xz"
  ],
  "Format": [
    "3.0 (native)"
  ],
  "Maintainer": [
    "Debian Install System Team \u003cdebian-boot@lists.debian.org\u003e"
  ],
  "Package": [
    "netcfg"
  ],
  "Package-List": [
    "netcfg udeb debian-installer optional arch=any netcfg-static udeb debian-installer optional arch=any"
  ],
  "Uploaders": [
    "Colin Watson \u003ccjwatson@debian.org\u003e"
  ],
  "Vcs-Browser": [
    "https://salsa.debian.org/installer-team/netcfg"
  ],
  "Vcs-Git": [
    "https://salsa.debian.org/installer-team/netcfg.git"
  ],
  "Version": [
    "1.197elxr1"
  ]
}