{
  "Architecture": [
    "any all"
  ],
  "Binary": [
    "graphviz, libgv-guile, libgv-lua, libgv-perl, python3-gv, libgv-ruby, libgv-tcl, libcgraph6, libcdt5, libpathplan4, libgvc6, libgvc6-plugins-gtk, libgvpr2, libxdot4, liblab-gamut1, libgraphviz-dev, graphviz-doc"
  ],
  "Build-Conflicts": [
    "tcl8.3, tcl8.4, tcl8.5"
  ],
  "Build-Depends": [
    "tk-dev, tcl-dev, debhelper-compat (= 13), dh-python, python3-setuptools, libfreetype-dev, zlib1g-dev, libjpeg-dev, libpng-dev, libxaw7-dev, bison, flex, libexpat1-dev, libfontconfig-dev, swig, libperl-dev, libgd-dev, guile-3.0-dev, groff-base, ghostscript, lua5.2, liblua5.2-dev, ruby [!ia64], ruby-dev (\u003e= 1:2.2) [!ia64], libargon2-dev, libsodium-dev, libxml2-dev, python3-dev, libcairo2-dev, libpango1.0-dev, d-shlibs, chrpath, libgtk2.0-dev, libgts-dev, libann-dev, librsvg2-dev, libwebp-dev"
  ],
  "Checksums-Sha1": [
    "d0571cde8e8df94795fcc7beacc8a25fdbf6ac33 40196 graphviz_2.42.4-3.debian.tar.xz 725e53fe9fb4101323c514b25f867f1370e7d12b 3163 graphviz_2.42.4-3.dsc fcf4f39e85e9d3282b65b84c5b53f66c623f860e 30699881 graphviz_2.42.4.orig.tar.bz2"
  ],
  "Checksums-Sha256": [
    "2416f1fc32aca3b3a74f5e178a2ed61ac7025d3c763aa382305077d63d7029db 40196 graphviz_2.42.4-3.debian.tar.xz ad2de2f55d9d73222aa4c47b9c3ec566a627cb25c533a268f5ffb8fcef00631f 3163 graphviz_2.42.4-3.dsc a1ca0c4273d96bbf32fbfcbb784c8da2e38da13e7d2bbf9b24fe94ae45e79c4c 30699881 graphviz_2.42.4.orig.tar.bz2"
  ],
  "Checksums-Sha512": [
    "1e098e4598d3fda88d4f075f246a1f0713c65d0d023a50cab1b2a4e26189bec579325db8d7f9d9c13d11a4b655fe6dc3a1ab10652341c60e20cc2a22522c0e7c 40196 graphviz_2.42.4-3.debian.tar.xz be8560b248c66183838b3da97e485fd90e6339235ee49cc3fe9699f1c15e579d63685c389029933f048edef503d7e750c13c3300b743f1fad87745666e5ec52b 3163 graphviz_2.42.4-3.dsc aa831069a45bfbfa2f570d60323e986f42685ea52e5217905b0f31d96d69b5776c6a1c2ce3fe48f5bbe6383146b0cfa867043d496acb281b1d50a46aa7e8856f 30699881 graphviz_2.42.4.orig.tar.bz2"
  ],
  "Directory": [
    "pool/main/g/graphviz"
  ],
  "Files": [
    "2e0a62fde6c3d6ca2ac298c16ce8ae8d 40196 graphviz_2.42.4-3.debian.tar.xz bfb6eef908b58f5c528a036b084616ee 3163 graphviz_2.42.4-3.dsc ea12f4ed9704c3cb59db241fa76303af 30699881 graphviz_2.42.4.orig.tar.bz2"
  ],
  "Format": [
    "3.0 (quilt)"
  ],
  "Homepage": [
    "https://www.graphviz.org/"
  ],
  "Maintainer": [
    "Laszlo Boszormenyi (GCS) \u003cgcs@debian.org\u003e"
  ],
  "Package": [
    "graphviz"
  ],
  "Package-List": [
    "graphviz deb graphics optional arch=any graphviz-doc deb doc optional arch=all libcdt5 deb libs optional arch=any libcgraph6 deb libs optional arch=any libgraphviz-dev deb libdevel optional arch=any libgv-guile deb interpreters optional arch=any libgv-lua deb interpreters optional arch=any libgv-perl deb perl optional arch=any libgv-ruby deb ruby optional arch=any libgv-tcl deb interpreters optional arch=any libgvc6 deb libs optional arch=any libgvc6-plugins-gtk deb libs optional arch=any libgvpr2 deb libs optional arch=any liblab-gamut1 deb libs optional arch=any libpathplan4 deb libs optional arch=any libxdot4 deb libs optional arch=any python3-gv deb python optional arch=any"
  ],
  "Standards-Version": [
    "4.7.0"
  ],
  "Testsuite": [
    "autopkgtest"
  ],
  "Testsuite-Triggers": [
    "file"
  ],
  "Version": [
    "2.42.4-3"
  ]
}