{
  "Architecture": [
    "alpha amd64 armel armhf arm64 i386 ia64 loong64 mips mipsel mips64 mips64el powerpc ppc64 ppc64el m68k riscv64 sh4 sparc sparc64 s390x x32 all"
  ],
  "Binary": [
    "openjdk-17-jdk-headless, openjdk-17-jre-headless, openjdk-17-jdk, openjdk-17-jre, openjdk-17-demo, openjdk-17-source, openjdk-17-doc, openjdk-17-dbg, openjdk-17-jre-zero"
  ],
  "Build-Depends": [
    "debhelper (\u003e= 11), m4, lsb-release, zip, unzip, sharutils, gawk, cpio, procps, wdiff, pkgconf, fastjar (\u003e= 2:0.96-0ubuntu2), time, strip-nondeterminism, debugedit (\u003e= 4.16), jtreg7 (\u003e= 7.3.1+1~) \u003c!nocheck\u003e, libtestng7-java \u003c!nocheck\u003e, xvfb \u003c!nocheck\u003e, xauth \u003c!nocheck\u003e, xfonts-base \u003c!nocheck\u003e, libgl1-mesa-dri [!x32] \u003c!nocheck\u003e, xfwm4 \u003c!nocheck\u003e, x11-xkb-utils \u003c!nocheck\u003e, dbus-x11 \u003c!nocheck\u003e, libasmtools-java \u003c!nocheck\u003e, autoconf, automake, ant, ant-optional, g++-12 \u003c!cross\u003e, openjdk-17-jdk-headless:native | openjdk-16-jdk-headless:native, libxtst-dev, libxi-dev, libxt-dev, libxaw7-dev, libxrender-dev, libcups2-dev, libasound2-dev, liblcms2-dev, libxinerama-dev, libkrb5-dev, xsltproc, libpcsclite-dev, libxrandr-dev, libelf-dev, libfontconfig-dev, libfreetype-dev, libharfbuzz-dev, libffi-dev, libffi-dev:native, zlib1g-dev:native, zlib1g-dev, libattr1-dev, libpng-dev, libjpeg-dev, libgif-dev, systemtap-sdt-dev [!powerpc !ppc64 !ppc64el !sh4 !s390x], libnss3-dev (\u003e= 2:3.17.1), openjdk-17-jdk-headless \u003ccross\u003e"
  ],
  "Build-Depends-Indep": [
    "graphviz, pandoc"
  ],
  "Checksums-Sha1": [
    "bd1338df8ad86f70e8d378a3aeaf22308208facf 204816 openjdk-17_17.0.15+6+dfsg2-0elxr12u1.debian.tar.xz f99b9b00ac679a57cfac43b5b82d3426e02492fc 4056 openjdk-17_17.0.15+6+dfsg2-0elxr12u1.dsc 8c19c28c61c0ecfae4463d0b7d55a37d43ac4a9c 612760 openjdk-17_17.0.15+6+dfsg2.orig-googletest.tar.xz bd61cea227f6a0a31aa9b4790683a0e023a95fbe 65653228 openjdk-17_17.0.15+6+dfsg2.orig.tar.xz"
  ],
  "Checksums-Sha256": [
    "cc35559c9959d0f3a6b9e5f5c39a59cb5f82c31e1d9ee7b05a1186081b2d17c3 204816 openjdk-17_17.0.15+6+dfsg2-0elxr12u1.debian.tar.xz 8d6f94ab2465b60f9ea1c2a9b1dfa74c529f5309dac76aea891958aaa06971cb 4056 openjdk-17_17.0.15+6+dfsg2-0elxr12u1.dsc 16b69ad52fdd369348848a7f44d23c5820978dc9fb59de8014a0bb3106268b8b 612760 openjdk-17_17.0.15+6+dfsg2.orig-googletest.tar.xz 0970f619ad62f9c268f520e31948f1b85bba14c949eb32d23298cd78f416f5bb 65653228 openjdk-17_17.0.15+6+dfsg2.orig.tar.xz"
  ],
  "Checksums-Sha512": [
    "7c0c383d9020bd4e153429019ae8f0b8a951e02c2bf03e84f1c89fab155d7482e88f8b38bfd577ab5ab8946e200de4ef13c38f6cd21ff339cf400dc23bd7854d 204816 openjdk-17_17.0.15+6+dfsg2-0elxr12u1.debian.tar.xz c5f52bc4c7585226f0a6e82c1ea78b6035dc3622967165d34420aef78660c7cd610cbcd8e3e923135899d912600fe5b4f44753539c5df422381392008ee351a9 4056 openjdk-17_17.0.15+6+dfsg2-0elxr12u1.dsc 93ebb96da1b9b77dd07152c91ad7da1957b9fbb17a45879c0c536f2e4157fd090a25cfff4c675d5ae0cce734039513f7e6cf8971d6f39ec36e5b12d40837aaaa 612760 openjdk-17_17.0.15+6+dfsg2.orig-googletest.tar.xz 866e266c7486883188b5be540bb770338a2e4f5b605d31ffc9f5d9e6268a20ff9ec49ad623dfbb70ecd5a5d2f3e4fe2484a0b5da26a1e92c78ed90f68fa3ee99 65653228 openjdk-17_17.0.15+6+dfsg2.orig.tar.xz"
  ],
  "Directory": [
    "pool/main/o/openjdk-17"
  ],
  "Files": [
    "d3a26e015bdd8d6844f9d857ff790774 204816 openjdk-17_17.0.15+6+dfsg2-0elxr12u1.debian.tar.xz 4d885e1294f23288d8052a9deb6f0fe7 4056 openjdk-17_17.0.15+6+dfsg2-0elxr12u1.dsc 988c58289937257e1ca96a91ca84fdab 612760 openjdk-17_17.0.15+6+dfsg2.orig-googletest.tar.xz 75bdebad981a0bdd532b31f74bf17928 65653228 openjdk-17_17.0.15+6+dfsg2.orig.tar.xz"
  ],
  "Format": [
    "3.0 (quilt)"
  ],
  "Homepage": [
    "https://openjdk.java.net/"
  ],
  "Maintainer": [
    "OpenJDK Team \u003copenjdk-17@packages.debian.org\u003e"
  ],
  "Package": [
    "openjdk-17"
  ],
  "Package-List": [
    "openjdk-17-dbg deb debug optional arch=alpha,amd64,armel,armhf,arm64,i386,ia64,loong64,mips,mipsel,mips64,mips64el,powerpc,ppc64,ppc64el,m68k,riscv64,sh4,sparc,sparc64,s390x,x32 openjdk-17-demo deb java optional arch=alpha,amd64,armel,armhf,arm64,i386,ia64,loong64,mips,mipsel,mips64,mips64el,powerpc,ppc64,ppc64el,m68k,riscv64,sh4,sparc,sparc64,s390x,x32 openjdk-17-doc deb doc optional arch=all openjdk-17-jdk deb java optional arch=alpha,amd64,armel,armhf,arm64,i386,ia64,loong64,mips,mipsel,mips64,mips64el,powerpc,ppc64,ppc64el,m68k,riscv64,sh4,sparc,sparc64,s390x,x32 openjdk-17-jdk-headless deb java optional arch=alpha,amd64,armel,armhf,arm64,i386,ia64,loong64,mips,mipsel,mips64,mips64el,powerpc,ppc64,ppc64el,m68k,riscv64,sh4,sparc,sparc64,s390x,x32 openjdk-17-jre deb java optional arch=alpha,amd64,armel,armhf,arm64,i386,ia64,loong64,mips,mipsel,mips64,mips64el,powerpc,ppc64,ppc64el,m68k,riscv64,sh4,sparc,sparc64,s390x,x32 openjdk-17-jre-headless deb java optional arch=alpha,amd64,armel,armhf,arm64,i386,ia64,loong64,mips,mipsel,mips64,mips64el,powerpc,ppc64,ppc64el,m68k,riscv64,sh4,sparc,sparc64,s390x,x32 openjdk-17-jre-zero deb java optional arch=amd64,i386,arm64,armhf,ppc64,ppc64el,riscv64,s390x openjdk-17-source deb java optional arch=all"
  ],
  "Standards-Version": [
    "4.6.2"
  ],
  "Testsuite": [
    "autopkgtest"
  ],
  "Uploaders": [
    "Matthias Klose \u003cdoko@ubuntu.com\u003e"
  ],
  "Vcs-Browser": [
    "https://salsa.debian.org/openjdk-team/openjdk/tree/openjdk-17"
  ],
  "Vcs-Git": [
    "https://salsa.debian.org/openjdk-team/openjdk.git -b openjdk-17"
  ],
  "Version": [
    "17.0.15+6+dfsg2-0elxr12u1"
  ]
}