{
  "Architecture": [
    "linux-any all"
  ],
  "Binary": [
    "gir1.2-ostree-1.0, libostree-1-1, libostree-dev, libostree-doc, ostree, ostree-boot, ostree-tests"
  ],
  "Build-Depends": [
    "attr, autoconf, automake, bison, bsdextrautils \u003c!nocheck\u003e, ca-certificates, cpio, debhelper-compat (= 13), dh-sequence-gir, docbook-xml \u003c!nodoc\u003e, docbook-xsl \u003c!nodoc\u003e, libext2fs-dev, elfutils, fuse3:native, gjs:native [!alpha !armel !hppa !ia64 !m68k !sh4 !sparc64 !x32], gnupg \u003c!nocheck\u003e, gobject-introspection, gtk-doc-tools \u003c!nodoc\u003e, libarchive-dev, libattr1-dev, libavahi-client-dev, libavahi-glib-dev, libcap-dev, libcurl4-gnutls-dev | libcurl-dev, libfuse3-dev, libgirepository1.0-dev, libglib2.0-dev, libgpgme-dev, liblzma-dev, libmount-dev, libselinux1-dev, libsoup-3.0-dev (\u003e= 3.0.0), libsystemd-dev, libtool, pkgconf, procps, python3 \u003c!nocheck\u003e, python3-yaml \u003c!nocheck\u003e, xsltproc \u003c!nodoc\u003e, zlib1g-dev"
  ],
  "Build-Depends-Indep": [
    "libglib2.0-doc"
  ],
  "Checksums-Sha1": [
    "fa6a8a1f73403a7e9c8f180e1dfa863697488e21 32744 ostree_2025.1-1elxr3b1.debian.tar.xz ddf92312256272decd6d45806aa6ebb1a1bb071b 2380 ostree_2025.1-1elxr3b1.dsc d1ad76514f2dcc673d1d6c38707b2f9cbd062632 2112364 ostree_2025.1.orig.tar.xz"
  ],
  "Checksums-Sha256": [
    "e80e7fd43b8af53257a062b19cd9fa8fb5d8c6bf157f60d5c906b6b9aee16758 32744 ostree_2025.1-1elxr3b1.debian.tar.xz a670eae1c07912ab27cde2cb44818ae9bf6be494508e96e147da4ec97c6fccf4 2380 ostree_2025.1-1elxr3b1.dsc f2c312344fd69ae42869f9817e7eb460b8daec81256a0d48afdc4e0ec2f18351 2112364 ostree_2025.1.orig.tar.xz"
  ],
  "Checksums-Sha512": [
    "d5765327c24ca8643b1b8e2039d61273865645cf394b0e0f37a286e5b52d5b3a5b86fd704ad3261bbd09641011d43f565b8d2ebdb270f6dbad7af416c5b29236 32744 ostree_2025.1-1elxr3b1.debian.tar.xz e0c9d0b6952d750720d5435612fce8f526b97d0d8577e35284e612e843d99f2e804c4f95b473bb7c65cf71a8ebb08a1afff85fbd00bc50b39d64de7d127de2ff 2380 ostree_2025.1-1elxr3b1.dsc ed699c9143a819ef289846ba4c10fc57af298f2d996982192091813a4e085e3e61faf04167d02c19b6bcf0efce64aa78658e3003558b33c5d09161c93ef728c0 2112364 ostree_2025.1.orig.tar.xz"
  ],
  "Directory": [
    "pool/main/o/ostree"
  ],
  "Files": [
    "3b4f19fdd14c30a4e79eeb59de1329ad 32744 ostree_2025.1-1elxr3b1.debian.tar.xz 5a5d268152029ed4e4c6bb58e7f03c24 2380 ostree_2025.1-1elxr3b1.dsc c99adc8cafde4f134cb0b5eaad010576 2112364 ostree_2025.1.orig.tar.xz"
  ],
  "Format": [
    "3.0 (quilt)"
  ],
  "Homepage": [
    "https://github.com/ostreedev/ostree/"
  ],
  "Maintainer": [
    "Utopia Maintenance Team \u003cpkg-utopia-maintainers@lists.alioth.debian.org\u003e"
  ],
  "Package": [
    "ostree"
  ],
  "Package-List": [
    "gir1.2-ostree-1.0 deb introspection optional arch=linux-any libostree-1-1 deb libs optional arch=linux-any libostree-dev deb libdevel optional arch=linux-any libostree-doc deb doc optional arch=all profile=!nodoc ostree deb admin optional arch=linux-any ostree-boot deb admin optional arch=linux-any ostree-tests deb admin optional arch=linux-any"
  ],
  "Standards-Version": [
    "4.7.0"
  ],
  "Testsuite": [
    "autopkgtest"
  ],
  "Testsuite-Triggers": [
    "build-essential, gnome-desktop-testing, pkgconf"
  ],
  "Uploaders": [
    "Matthias Klumpp \u003cmak@debian.org\u003e, Simon McVittie \u003csmcv@debian.org\u003e, Sjoerd Simons \u003csjoerd@debian.org\u003e, Dylan Aïssi \u003cdaissi@debian.org\u003e"
  ],
  "Vcs-Browser": [
    "https://salsa.debian.org/debian/ostree"
  ],
  "Vcs-Git": [
    "https://salsa.debian.org/debian/ostree.git"
  ],
  "Version": [
    "2025.1-1elxr3b1"
  ]
}