{
  "Architecture": [
    "all"
  ],
  "Binary": [
    "python-os-vif-doc, python3-os-vif"
  ],
  "Build-Depends": [
    "debhelper-compat (= 10), dh-python, openstack-pkg-tools, python3-all, python3-pbr, python3-setuptools, python3-sphinx"
  ],
  "Build-Depends-Indep": [
    "python3-coverage, python3-debtcollector, python3-hacking, python3-openstackdocstheme, python3-oslo.concurrency, python3-oslo.config, python3-oslo.i18n, python3-oslo.log, python3-oslo.privsep, python3-oslo.serialization, python3-oslo.utils, python3-oslo.versionedobjects, python3-oslosphinx, python3-oslotest \u003c!nocheck\u003e, python3-ovsdbapp, python3-pyroute2, python3-reno, python3-stestr \u003c!nocheck\u003e, python3-stevedore, python3-testscenarios \u003c!nocheck\u003e, subunit \u003c!nocheck\u003e"
  ],
  "Checksums-Sha1": [
    "b4953a7c61d942442c67e38678dec37c99b4bfeb 3984 python-os-vif_4.1.0-2.debian.tar.xz 885ba8df429596ed1d4bff3a9eff1941d6b6ffe5 2718 python-os-vif_4.1.0-2.dsc 08d193bc2afe9ea3fcba6defc9931f213d7811ae 71892 python-os-vif_4.1.0.orig.tar.xz"
  ],
  "Checksums-Sha256": [
    "4ad4dfc6a8656567cff03fcab9b61a4b040f4c96bd0082051a6d57d1a349104a 3984 python-os-vif_4.1.0-2.debian.tar.xz 0ec83cfcfff61910e5fd1501f9f2fe48b7fc181b50ab67010b8f53d5f1a3c25c 2718 python-os-vif_4.1.0-2.dsc 80203c1ecb72390368b5156f483f63d7af1c0b9aad5b3443b1fef74ad3cf2031 71892 python-os-vif_4.1.0.orig.tar.xz"
  ],
  "Checksums-Sha512": [
    "3947bd7a01e2411bfb6059bf89e91cec4ed6f0534c2556741da56fb4e6fc3eb4f9cdb1a9e03d468bc623d3440521bb0c164c7de11d13e1b6e7a99c310a6bf137 3984 python-os-vif_4.1.0-2.debian.tar.xz 5e106868ddf52c5a70895e563583d89ba63648b8aa46ba692c52944f27a390ce19511bf8224ca8937bc535eaf0880b46d94d2396c744aa6a74c542a92d732f41 2718 python-os-vif_4.1.0-2.dsc 5ac9bf9e57f045a9efd1cc1b63307872cee1870313584de151a5a1b2f47d4950837dc841537e70a43979f0a13ac0412a2a680853ca03a9799005b59f9b0b042b 71892 python-os-vif_4.1.0.orig.tar.xz"
  ],
  "Directory": [
    "pool/main/p/python-os-vif"
  ],
  "Files": [
    "3e2879fddcbcc6aeb958cec777477450 3984 python-os-vif_4.1.0-2.debian.tar.xz 5993cc4640cd5af62e2688db6cd4aa0b 2718 python-os-vif_4.1.0-2.dsc bf57a92657c2e92f702798ae86f6056d 71892 python-os-vif_4.1.0.orig.tar.xz"
  ],
  "Format": [
    "3.0 (quilt)"
  ],
  "Homepage": [
    "https://github.com/openstack/os-vif"
  ],
  "Maintainer": [
    "Debian OpenStack \u003cteam+openstack@tracker.debian.org\u003e"
  ],
  "Package": [
    "python-os-vif"
  ],
  "Package-List": [
    "python-os-vif-doc deb doc optional arch=all python3-os-vif deb python optional arch=all"
  ],
  "Standards-Version": [
    "4.1.3"
  ],
  "Testsuite": [
    "autopkgtest"
  ],
  "Testsuite-Triggers": [
    "@builddeps@"
  ],
  "Uploaders": [
    "Ivan Udovichenko \u003ciudovichenko@mirantis.com\u003e, Thomas Goirand \u003czigo@debian.org\u003e,"
  ],
  "Vcs-Browser": [
    "https://salsa.debian.org/openstack-team/libs/python-os-vif"
  ],
  "Vcs-Git": [
    "https://salsa.debian.org/openstack-team/libs/python-os-vif.git"
  ],
  "Version": [
    "4.1.0-2"
  ]
}