{
  "Architecture": [
    "any"
  ],
  "Binary": [
    "libmouse-perl"
  ],
  "Build-Depends": [
    "debhelper-compat (= 12), libclass-method-modifiers-perl \u003c!nocheck\u003e, libio-string-perl \u003c!nocheck\u003e, liblocale-us-perl \u003c!nocheck\u003e, libmodule-build-perl, libmodule-build-xsutil-perl (\u003e= 0.19), libmoose-perl \u003c!nocheck\u003e, libparams-coerce-perl \u003c!nocheck\u003e, libpath-class-perl \u003c!nocheck\u003e, libregexp-common-perl \u003c!nocheck\u003e, libtest-deep-perl \u003c!nocheck\u003e, libtest-exception-perl \u003c!nocheck\u003e, libtest-fatal-perl \u003c!nocheck\u003e, libtest-leaktrace-perl \u003c!nocheck\u003e, libtest-output-perl \u003c!nocheck\u003e, libtest-requires-perl \u003c!nocheck\u003e, libtry-tiny-perl \u003c!nocheck\u003e, liburi-perl \u003c!nocheck\u003e, libwww-perl \u003c!nocheck\u003e, perl-xs-dev, perl:native (\u003e= 5.25.3)"
  ],
  "Checksums-Sha1": [
    "48432b3d6d3f2fa72a937d2d2383357eb4754d6c 6632 libmouse-perl_2.5.10-1.debian.tar.xz 4ac454df6e903916811c1e64138c22bb8f8c94be 2957 libmouse-perl_2.5.10-1.dsc beba7239482a5f656e7889632a9aadfaeae2fcd6 220349 libmouse-perl_2.5.10.orig.tar.gz"
  ],
  "Checksums-Sha256": [
    "f98eba2087567bf4ea1759615b3f4446d84d13012b08baeef4e9e4458fa292c5 6632 libmouse-perl_2.5.10-1.debian.tar.xz f9e1bfe22bb36b3c765909330e9bd419b4c8897560ff4c2a0deec2569baeafa2 2957 libmouse-perl_2.5.10-1.dsc ce8dc23946153a467ff09765167ee2590f5c502120f48a2d9441733f39aa32ee 220349 libmouse-perl_2.5.10.orig.tar.gz"
  ],
  "Checksums-Sha512": [
    "a81376e50a83121222b6f27caee6aa348f6b652574a4e04d4a7a26f475e4b543b0d261a8ec1ec07ff1ae1f214093cfa936207f881800522e29b83878a2997e45 6632 libmouse-perl_2.5.10-1.debian.tar.xz 05aca0172515a927f19812a5a59bca85062aceefd3c88530c30cb91a95b76642b7ed664ee3019936dfa104f8ff8690b2ccc6d192dcc4706db223e6ac9725710d 2957 libmouse-perl_2.5.10-1.dsc 949a2f18257a5afcf4dbbb84094974f4d80e1e4531b4b9d8618cf141252fd11b09b79daafe1de79faa620905988f649627bc2fceac357ea2f180db74cd48f711 220349 libmouse-perl_2.5.10.orig.tar.gz"
  ],
  "Dgit": [
    "04c5dff992e16b916b5a70e78ac30edee6537b4a debian archive/debian/2.5.10-1 https://git.dgit.debian.org/libmouse-perl"
  ],
  "Directory": [
    "pool/main/libm/libmouse-perl"
  ],
  "Files": [
    "da5708d541400d12cc4ad25e81f225d5 6632 libmouse-perl_2.5.10-1.debian.tar.xz 12c7b829f6d639fb755ced8f39e5fbb7 2957 libmouse-perl_2.5.10-1.dsc 0dd19d703e14af71d723ba787d631858 220349 libmouse-perl_2.5.10.orig.tar.gz"
  ],
  "Format": [
    "3.0 (quilt)"
  ],
  "Homepage": [
    "https://metacpan.org/release/Mouse"
  ],
  "Maintainer": [
    "Debian Perl Group \u003cpkg-perl-maintainers@lists.alioth.debian.org\u003e"
  ],
  "Package": [
    "libmouse-perl"
  ],
  "Package-List": [
    "libmouse-perl deb perl optional arch=any"
  ],
  "Standards-Version": [
    "4.5.0"
  ],
  "Testsuite": [
    "autopkgtest-pkg-perl"
  ],
  "Uploaders": [
    "gregor herrmann \u003cgregoa@debian.org\u003e, Ansgar Burchardt \u003cansgar@debian.org\u003e, Dominic Hargreaves \u003cdom@earth.li\u003e"
  ],
  "Vcs-Browser": [
    "https://salsa.debian.org/perl-team/modules/packages/libmouse-perl"
  ],
  "Vcs-Git": [
    "https://salsa.debian.org/perl-team/modules/packages/libmouse-perl.git"
  ],
  "Version": [
    "2.5.10-1"
  ]
}