{
  "Architecture": [
    "arm64"
  ],
  "Binary": [
    "linux-image-6.1.0-42-cloud-arm64, linux-image-cloud-arm64, linux-headers-cloud-arm64"
  ],
  "Build-Depends": [
    "debhelper-compat (= 12), dh-exec, python3:any, rsync, sbsigntool [amd64 arm64 i386], kernel-wedge (\u003e= 2.102~), linux-arm64-support-6.1.0-42 (= 6.1.159-elxr2-1), linux-image-6.1.0-42-cloud-arm64-unsigned (= 6.1.159-elxr2-1) [arm64]"
  ],
  "Checksums-Sha1": [
    "34c8ff6e7bd673bc99c61dc7eb8c3cc6afe90574 1370 linux-arm64-signed-arm64_6.1.159+elxr2+1.dsc e56d6684adea0bba1aaf9af0e7af4caef271922e 785296 linux-arm64-signed-arm64_6.1.159+elxr2+1.tar.xz"
  ],
  "Checksums-Sha256": [
    "cbaed1b2d7bee88a2a95a331d3dfeaa071a7ceaf5ba5dfab99d5d39e2a395d3f 1370 linux-arm64-signed-arm64_6.1.159+elxr2+1.dsc 145151dd5f18a3d01678a654e4ccebb3ed4162cb7c76a176844cab1123e142d2 785296 linux-arm64-signed-arm64_6.1.159+elxr2+1.tar.xz"
  ],
  "Checksums-Sha512": [
    "b3ce584fdd2b343abd3993598a46ce97f86ab7466cba339a5d7051bb629aef10b680273394c8e62ee23d03702f5dbe5547b3d95e0041869935c728dda49308fc 1370 linux-arm64-signed-arm64_6.1.159+elxr2+1.dsc 22a627dfc8c83b92e2f0198969e1dfbb0a6e23b68c03e9593146a17bd924f3c7aa984168b334950a02f4898b157ec217b261cf8f02d92fc86ff2e9a5b47406c7 785296 linux-arm64-signed-arm64_6.1.159+elxr2+1.tar.xz"
  ],
  "Directory": [
    "pool/main/l/linux-arm64-signed-arm64"
  ],
  "Files": [
    "1aae015c9292410064a21ffea1fd9721 1370 linux-arm64-signed-arm64_6.1.159+elxr2+1.dsc 2b78f124fdb2bc25c85a2dde6fd5c84b 785296 linux-arm64-signed-arm64_6.1.159+elxr2+1.tar.xz"
  ],
  "Format": [
    "3.0 (native)"
  ],
  "Homepage": [
    "https://www.kernel.org/"
  ],
  "Maintainer": [
    "Debian Kernel Team \u003cdebian-kernel@lists.debian.org\u003e"
  ],
  "Package": [
    "linux-arm64-signed-arm64"
  ],
  "Package-List": [
    "linux-headers-cloud-arm64 deb kernel optional arch=arm64 linux-image-6.1.0-42-cloud-arm64 deb kernel optional arch=arm64 linux-image-cloud-arm64 deb kernel optional arch=arm64"
  ],
  "Standards-Version": [
    "4.2.0"
  ],
  "Uploaders": [
    "Bastian Blank \u003cwaldi@debian.org\u003e, maximilian attems \u003cmaks@debian.org\u003e, Ben Hutchings \u003cbenh@debian.org\u003e, Salvatore Bonaccorso \u003ccarnil@debian.org\u003e"
  ],
  "Vcs-Browser": [
    "https://salsa.debian.org/kernel-team/linux"
  ],
  "Vcs-Git": [
    "https://salsa.debian.org/kernel-team/linux.git"
  ],
  "Version": [
    "6.1.159+elxr2+1"
  ]
}