{
  "Architecture": [
    "all"
  ],
  "Binary": [
    "nvimpager"
  ],
  "Build-Depends": [
    "debhelper-compat (= 13), lua-busted \u003c!nocheck\u003e, neovim \u003c!nocheck\u003e, procps \u003c!nocheck\u003e, scdoc"
  ],
  "Checksums-Sha256": [
    "a6f5988a82aad7a9b5e4ab1801570f1ac0f65108dbc1c55c86c09d8fa37cfd5e 1293 nvimpager_0.13.0-1.dsc 8255c39697b213cb34dfd573d90c27db7f61180d4a12f640ef6e7f313e525241 33459 nvimpager_0.13.0.orig.tar.gz ab49c77f34048cb1d1d457719f4c2d80fcdf17c7436f58fd4282210430b0a077 2292 nvimpager_0.13.0-1.debian.tar.xz"
  ],
  "Directory": [
    "pool/main/n/nvimpager"
  ],
  "Files": [
    "5ba189287162412d5bd87c640ddffb0f 1293 nvimpager_0.13.0-1.dsc fc93e76708b7d1345509cb7ba31d189e 33459 nvimpager_0.13.0.orig.tar.gz a00710637d007fbc9bcfa8a813f95a85 2292 nvimpager_0.13.0-1.debian.tar.xz"
  ],
  "Format": [
    "3.0 (quilt)"
  ],
  "Homepage": [
    "https://github.com/lucc/nvimpager"
  ],
  "Maintainer": [
    "Michael Lloyd \u003cmichael@micl.dev\u003e"
  ],
  "Package": [
    "nvimpager"
  ],
  "Package-List": [
    "nvimpager deb text optional arch=all"
  ],
  "Priority": [
    "optional"
  ],
  "Section": [
    "text"
  ],
  "Standards-Version": [
    "4.7.3"
  ],
  "Vcs-Browser": [
    "https://salsa.debian.org/micl/nvimpager"
  ],
  "Vcs-Git": [
    "https://salsa.debian.org/micl/nvimpager.git"
  ],
  "Version": [
    "0.13.0-1"
  ]
}