{
  "Architecture": [
    "linux-any all"
  ],
  "Binary": [
    "libqt6bluetooth6, libqt6bluetooth6-bin, libqt6nfc6, qt6-connectivity-dev, qt6-connectivity-doc, qt6-connectivity-doc-html, qt6-connectivity-examples"
  ],
  "Build-Depends": [
    "debhelper-compat (= 13), cmake (\u003e= 3.24~), libbluetooth-dev [linux-any], libgl-dev, libpcsclite-dev, libssl-dev, libvulkan-dev [linux-any], ninja-build, pkg-kde-tools, pkgconf, qt6-base-dev (\u003e= 6.8.2+dfsg~), qt6-base-private-dev (\u003e= 6.8.2+dfsg~), qt6-declarative-dev (\u003e= 6.8.2+dfsg~), qt6-declarative-private-dev"
  ],
  "Build-Depends-Indep": [
    "qt6-base-dev (\u003e= 6.8~) \u003c!nodoc\u003e, qt6-documentation-tools (\u003e= 6.8~) \u003c!nodoc\u003e"
  ],
  "Checksums-Sha1": [
    "ea7f34da4c55d7a651bc63707361f8b1484e049d 12672 qt6-connectivity_6.8.2-3.debian.tar.xz 16fc5327299e69d5f408b419c82163c6df4365d3 2889 qt6-connectivity_6.8.2-3.dsc 7a5f45c0d0b059459b73540a0eadd06a230fac7e 1069068 qt6-connectivity_6.8.2.orig.tar.xz"
  ],
  "Checksums-Sha256": [
    "07fbeb2789d5833e0ea2176bab519c3db09677e239bcc7dc1c8e5888679e8cdf 12672 qt6-connectivity_6.8.2-3.debian.tar.xz 762e2ee9959e7e35fc4b32b341015604ae353fbc3a7295c5fd6cc0a8ab3460bc 2889 qt6-connectivity_6.8.2-3.dsc e617120e084ac369fd6064f2c177de9e1c2cd9989a1f1774eea131800d52812a 1069068 qt6-connectivity_6.8.2.orig.tar.xz"
  ],
  "Checksums-Sha512": [
    "e6dd067e1a92cb292c326f7cd5bd5191d712a060a7f7b423b26b8511d36d9b8049e0075488d40b2d541d58ba603b8e8f13acfdd0869ed3678b5594e1d63f70bd 12672 qt6-connectivity_6.8.2-3.debian.tar.xz d08ce3c0df558ba6e6228babf2cf83e63e6e449fb6c7017874b4bb0e89641c05b7f5e22625c3204ef498e64fcf973bdd86229f0e5bc0c5db79aa066f4afca71d 2889 qt6-connectivity_6.8.2-3.dsc b1310fc90c7a64a4d89586fd38119377b3b67ead57271c6713897d649b2154cd55bd07c97a53f12e7a9d720a1b8b6b630eeea43e44c6798f6313ea8e70e10767 1069068 qt6-connectivity_6.8.2.orig.tar.xz"
  ],
  "Directory": [
    "pool/main/q/qt6-connectivity"
  ],
  "Files": [
    "b09bda24760804ec4e24f6e80609d66c 12672 qt6-connectivity_6.8.2-3.debian.tar.xz 30a7ec4e96f9f6ff35ed0e2098fcddd0 2889 qt6-connectivity_6.8.2-3.dsc 4a12e44340771a60da2054196716eca4 1069068 qt6-connectivity_6.8.2.orig.tar.xz"
  ],
  "Format": [
    "3.0 (quilt)"
  ],
  "Homepage": [
    "https://www.qt.io/developers/"
  ],
  "Maintainer": [
    "Debian Qt/KDE Maintainers \u003cdebian-qt-kde@lists.debian.org\u003e"
  ],
  "Package": [
    "qt6-connectivity"
  ],
  "Package-List": [
    "libqt6bluetooth6 deb libs optional arch=linux-any libqt6bluetooth6-bin deb utils optional arch=linux-any libqt6nfc6 deb libs optional arch=linux-any qt6-connectivity-dev deb libdevel optional arch=linux-any qt6-connectivity-doc deb doc optional arch=all qt6-connectivity-doc-html deb doc optional arch=all qt6-connectivity-examples deb misc optional arch=linux-any"
  ],
  "Standards-Version": [
    "4.7.0"
  ],
  "Uploaders": [
    "Patrick Franz \u003cdeltaone@debian.org\u003e, Lu YaNing \u003cdluyaning@gmail.com\u003e,"
  ],
  "Vcs-Browser": [
    "https://salsa.debian.org/qt-kde-team/qt6/qt6-connectivity"
  ],
  "Vcs-Git": [
    "https://salsa.debian.org/qt-kde-team/qt6/qt6-connectivity.git"
  ],
  "Version": [
    "6.8.2-3"
  ]
}