{
  "Architecture": [
    "any all"
  ],
  "Binary": [
    "libqt5contacts5a, qml-module-qtcontacts, libqt5organizer5a, qml-module-qtorganizer, libqt5versit5a, libqt5versitorganizer5a, qtpim5-dev, qtpim5-private-dev, qtpim5-doc, qtpim5-doc-html, qtpim5-examples"
  ],
  "Build-Depends": [
    "dbus, debhelper-compat (= 13), pkg-kde-tools, qml-module-qtquick2, qml-module-qttest, qtbase5-private-dev, qtdeclarative5-private-dev, qttools5-dev-tools, rdfind, symlinks, xauth \u003c!nocheck\u003e, xvfb \u003c!nocheck\u003e"
  ],
  "Build-Depends-Indep": [
    "qdoc-qt5, qtbase5-doc-html, qtdeclarative5-doc-html"
  ],
  "Checksums-Sha1": [
    "02d7ece60ed70c05567d97c58255f304aee2b89e 60100 qtpim-opensource-src_5.0~git20201102.f9a8f0fc+dfsg1-6.debian.tar.xz 6fc919794bdc40de877bfc8c8a8aa5001a9f7ad6 3206 qtpim-opensource-src_5.0~git20201102.f9a8f0fc+dfsg1-6.dsc d59d60f0296dd7a692b37458f2ab108f5ed3f611 1629040 qtpim-opensource-src_5.0~git20201102.f9a8f0fc+dfsg1.orig.tar.xz"
  ],
  "Checksums-Sha256": [
    "b8b446349ee562fe665b95d31324cc998e517180976473b1912ef78ecdbb5326 60100 qtpim-opensource-src_5.0~git20201102.f9a8f0fc+dfsg1-6.debian.tar.xz 58bec8b4c75e806ca6f192734b1acb08792309514400fe8ce69d4f7c2ec731d0 3206 qtpim-opensource-src_5.0~git20201102.f9a8f0fc+dfsg1-6.dsc 4b4bbbb87e553dd65c031957c55382211d835a32b700f1c3f6590ab27d65f14f 1629040 qtpim-opensource-src_5.0~git20201102.f9a8f0fc+dfsg1.orig.tar.xz"
  ],
  "Checksums-Sha512": [
    "9987335e03decbaba8fd159fad910707da49cf26474b5273b28e0ed351972eeaae37741a1dacefeab00bca4ec231d8d8e6147690e0f6bf93707830dbabb1bfd0 60100 qtpim-opensource-src_5.0~git20201102.f9a8f0fc+dfsg1-6.debian.tar.xz f94e0b3329ae63f0d175819ccb90844b8e2cdfaec458bec356fd62365c9cb8cf93164a25ede1c022788767860d5587671dce97cf87dd0777e57cfcc2afe9efc2 3206 qtpim-opensource-src_5.0~git20201102.f9a8f0fc+dfsg1-6.dsc 206fd02db9247fff6773600b0acfb53c76863cb8181fd2bad5dc8be508742739e1dab1c4d94545c9e9e2f7d4a3ac30de6b135cf79535ef47575c5e3289a53a8d 1629040 qtpim-opensource-src_5.0~git20201102.f9a8f0fc+dfsg1.orig.tar.xz"
  ],
  "Directory": [
    "pool/main/q/qtpim-opensource-src"
  ],
  "Files": [
    "81338bab1da579b25c53a5b79b401d66 60100 qtpim-opensource-src_5.0~git20201102.f9a8f0fc+dfsg1-6.debian.tar.xz 2958544fabf1d3b6ae9ae61a406fab3a 3206 qtpim-opensource-src_5.0~git20201102.f9a8f0fc+dfsg1-6.dsc 7504fd31c7ed902169248402ededfef3 1629040 qtpim-opensource-src_5.0~git20201102.f9a8f0fc+dfsg1.orig.tar.xz"
  ],
  "Format": [
    "3.0 (quilt)"
  ],
  "Homepage": [
    "https://www.qt.io/developers"
  ],
  "Maintainer": [
    "Debian Qt/KDE Maintainers \u003cdebian-qt-kde@lists.debian.org\u003e"
  ],
  "Package": [
    "qtpim-opensource-src"
  ],
  "Package-List": [
    "libqt5contacts5a deb libs optional arch=any libqt5organizer5a deb libs optional arch=any libqt5versit5a deb libs optional arch=any libqt5versitorganizer5a deb libs optional arch=any qml-module-qtcontacts deb libs optional arch=any qml-module-qtorganizer deb libs optional arch=any qtpim5-dev deb libdevel optional arch=any qtpim5-doc deb doc optional arch=all qtpim5-doc-html deb doc optional arch=all qtpim5-examples deb libdevel optional arch=any qtpim5-private-dev deb libdevel optional arch=any"
  ],
  "Standards-Version": [
    "4.7.0"
  ],
  "Uploaders": [
    "Debian UBports Team \u003cteam+ubports@tracker.debian.org\u003e, Timo Jyrinki \u003ctimo@debian.org\u003e, Mike Gabriel \u003csunweaver@debian.org\u003e,"
  ],
  "Vcs-Browser": [
    "https://salsa.debian.org/qt-kde-team/qt/qtpim/"
  ],
  "Vcs-Git": [
    "https://salsa.debian.org/qt-kde-team/qt/qtpim.git"
  ],
  "Version": [
    "5.0~git20201102.f9a8f0fc+dfsg1-6"
  ]
}