{
  "Architecture": [
    "linux-any all"
  ],
  "Binary": [
    "libcamera-dev, libcamera-doc, libcamera0.4, libcamera-ipa, libcamera-tools, libcamera-v4l2, gstreamer1.0-libcamera, python3-libcamera"
  ],
  "Build-Depends": [
    "debhelper-compat (= 13), dh-sequence-python3, libdrm-dev \u003c!pkg.libcamera.nosdl\u003e, libdw-dev \u003c!pkg.libcamera.notrace\u003e, libevent-dev, libgnutls28-dev | gnutls-dev, libgstreamer-plugins-base1.0-dev, libgstreamer1.0-dev, libgtest-dev \u003c!nocheck\u003e, libjpeg-dev \u003c!pkg.libcamera.nosdl\u003e, liblttng-ust-dev [!hurd-any !i386], libpython3-dev \u003c!pkg.libcamera.nopython\u003e, libsdl2-dev \u003c!pkg.libcamera.nosdl\u003e, libtiff-dev, libudev-dev [linux-any], libyaml-dev, libyuv-dev, meson (\u003e= 0.63), openssl, pkgconf, python3-jinja2, python3-ply, python3-pybind11 \u003c!pkg.libcamera.nopython\u003e, python3-yaml, qt6-base-dev [!i386] \u003c!pkg.libcamera.noqt\u003e"
  ],
  "Build-Depends-Indep": [
    "doxygen \u003c!nodoc\u003e, doxygen-latex \u003c!nodoc\u003e, graphviz \u003c!nodoc\u003e, libjs-jquery \u003c!nodoc\u003e, libjs-sphinxdoc \u003c!nodoc\u003e, libjs-underscore \u003c!nodoc\u003e, python3-sphinx \u003c!nodoc\u003e"
  ],
  "Checksums-Sha1": [
    "85addbc024a72b57a9faeb7ac5b03ee6bc4fb63b 24448 libcamera_0.4.0-7.debian.tar.xz d436f00a154d1324e175ba701a2fc98c94723e3a 3424 libcamera_0.4.0-7.dsc 1b03222a4f73ad7a410ac80897c10660ba27d340 1315742 libcamera_0.4.0.orig.tar.bz2"
  ],
  "Checksums-Sha256": [
    "e1e1a9a0726cf7e446926ac849018a02f9b497951062e1982be761a039ce6271 24448 libcamera_0.4.0-7.debian.tar.xz 4bea748710fdc0dec694e19e0a838f4329da5f8fc851725a8820848cbda46279 3424 libcamera_0.4.0-7.dsc 32a0a2b91f03f16a191b8fbe48fdcf886e8153c367569301bfd1bf70ebb4dcc0 1315742 libcamera_0.4.0.orig.tar.bz2"
  ],
  "Checksums-Sha512": [
    "f26a70f3dc863f22e4c929cd052339b9100a77c27bb20693e0b47298cf1d7be9acafa3d4fa39b2730fc24d4b220c1e29315cf88d4eaf765864ed3b36e3bdda9f 24448 libcamera_0.4.0-7.debian.tar.xz f5495ffc2249850858df6701fb3d9a688d90625c3e6bf93618a3fd3c5a33983e1ec5581fcd1c13b02aad9d37455401bf4bdc7a584925317a5d681c7ded49e766 3424 libcamera_0.4.0-7.dsc dd097461cc5bc834cdd6c43e872a32aee55ee7276b850600d705461aa9279144163b6d0374a63b27bec3f866973d4a44a9f89eacf1d40468a33faec1ffbc75b4 1315742 libcamera_0.4.0.orig.tar.bz2"
  ],
  "Directory": [
    "pool/main/libc/libcamera"
  ],
  "Files": [
    "e023bf69c14c03d6b3b089b77381e0ab 24448 libcamera_0.4.0-7.debian.tar.xz 46f286e59b777bad98593d7fba99081b 3424 libcamera_0.4.0-7.dsc b20f54559e80c1c4fd79e95774e8e98a 1315742 libcamera_0.4.0.orig.tar.bz2"
  ],
  "Format": [
    "3.0 (quilt)"
  ],
  "Homepage": [
    "https://libcamera.org/"
  ],
  "Maintainer": [
    "Debian Multimedia Maintainers \u003cdebian-multimedia@lists.debian.org\u003e"
  ],
  "Package": [
    "libcamera"
  ],
  "Package-List": [
    "gstreamer1.0-libcamera deb libs optional arch=linux-any libcamera-dev deb libdevel optional arch=linux-any libcamera-doc deb doc optional arch=all profile=!nodoc libcamera-ipa deb libs optional arch=linux-any libcamera-tools deb video optional arch=linux-any libcamera-v4l2 deb libs optional arch=linux-any libcamera0.4 deb libs optional arch=linux-any python3-libcamera deb python optional arch=linux-any"
  ],
  "Standards-Version": [
    "4.7.2"
  ],
  "Testsuite": [
    "autopkgtest"
  ],
  "Testsuite-Triggers": [
    "@builddeps@, gstreamer1.0-tools"
  ],
  "Uploaders": [
    "Emmanuel Arias \u003cemmanuelarias30@gmail.com\u003e, IOhannes m zmölnig (Debian/GNU) \u003cumlaeute@debian.org\u003e, Andrej Shadura \u003candrewsh@debian.org\u003e, Dylan Aïssi \u003cdaissi@debian.org\u003e"
  ],
  "Vcs-Browser": [
    "https://salsa.debian.org/multimedia-team/libcamera"
  ],
  "Vcs-Git": [
    "https://salsa.debian.org/multimedia-team/libcamera.git"
  ],
  "Version": [
    "0.4.0-7"
  ]
}