{
  "Architecture": [
    "any all"
  ],
  "Binary": [
    "libsoup-3.0-dev, libsoup-3.0-0, libsoup-3.0-common, libsoup-3.0-doc, gir1.2-soup-3.0, libsoup-3.0-tests"
  ],
  "Build-Depends": [
    "apache2 (\u003e= 2.4) \u003c!nocheck\u003e \u003c!noinsttest\u003e, ca-certificates \u003c!nocheck\u003e \u003c!noinsttest\u003e, curl \u003c!nocheck\u003e \u003c!noinsttest\u003e, debhelper-compat (= 13), dh-sequence-gir, dh-sequence-gnome, glib-networking (\u003e= 2.32.0), gi-docgen, libapache2-mod-php (\u003c\u003c 2:9) \u003c!nocheck\u003e \u003c!noinsttest\u003e, libapache2-mod-php (\u003e= 2:7) \u003c!nocheck\u003e \u003c!noinsttest\u003e, libbrotli-dev, libgirepository1.0-dev (\u003e= 0.9.5), libglib2.0-dev (\u003e= 2.69), libgnutls28-dev (\u003e= 3.6.0) \u003c!nocheck\u003e, libkrb5-dev, libnghttp2-dev, libnss-myhostname [linux-any] \u003c!nocheck\u003e, libpsl-dev (\u003e= 0.20), libsqlite3-dev, libsysprof-capture-4-dev [!hppa !hurd-i386 !kfreebsd-amd64 !kfreebsd-i386], meson (\u003e= 0.54), php (\u003c\u003c 2:9) \u003c!nocheck\u003e \u003c!noinsttest\u003e, php (\u003e= 2:7) \u003c!nocheck\u003e \u003c!noinsttest\u003e, python3-quart \u003c!nocheck\u003e, valac, winbind"
  ],
  "Build-Depends-Indep": [
    "libglib2.0-doc"
  ],
  "Checksums-Sha1": [
    "18c39cf2ccdbe8bafae6ea5cb9fcee000ff89f92 38208 libsoup3_3.2.3-0+deb12u2.debian.tar.xz 109f78b0454e2dfb3c04d7580032cf1653adbbc7 3514 libsoup3_3.2.3-0+deb12u2.dsc 104cbce77f3d620c9b6660f03c6c8076a2c99711 1530552 libsoup3_3.2.3.orig.tar.xz"
  ],
  "Checksums-Sha256": [
    "34a04a865a644a16d635f55454ba06d52329806de943a95ed245384e6ea077b6 38208 libsoup3_3.2.3-0+deb12u2.debian.tar.xz b00656d3dc925048e575643f7ea701ffc3d1e2ec677372b77255284e0b810be6 3514 libsoup3_3.2.3-0+deb12u2.dsc 3f50c2a883d7e984e31ecbaa35326b4e6bc6357bd3eed9bb4eb49154ebadd2fd 1530552 libsoup3_3.2.3.orig.tar.xz"
  ],
  "Checksums-Sha512": [
    "791cafb3fde16e067250fc2d157710d0a169cd630eb959e16ae7a56560b1e026eefe06b1131d359ebe5cf7e4018a674799471d69d068e3a82c072bffc0d17f47 38208 libsoup3_3.2.3-0+deb12u2.debian.tar.xz 75ab7454a41f218a2863e94f38c7c4473b624504ef63cc4db925bbb564f13e4c0ed9f57097543953585c687f4540bb646bc8f46a5992192dc6d82429d1257f68 3514 libsoup3_3.2.3-0+deb12u2.dsc 52775764b0b2789f414e5a694a86be0fa4e95cc9bf45e4cee9ccb1af4258f28694a4513f7f4762c77769429c7bd54b76ad1bdafc067b2d83660bbabb68764148 1530552 libsoup3_3.2.3.orig.tar.xz"
  ],
  "Dgit": [
    "aabc3e01ba7a3f804efad32dff6999d88f7af0ae debian archive/debian/3.2.3-0+deb12u2 https://git.dgit.debian.org/libsoup3"
  ],
  "Directory": [
    "pool/main/libs/libsoup3"
  ],
  "Files": [
    "ebaf706e41784c7ecdac04475eaa8674 38208 libsoup3_3.2.3-0+deb12u2.debian.tar.xz ecaa011c29a9237de552df9ec26cd29f 3514 libsoup3_3.2.3-0+deb12u2.dsc c609e3028296f559786fa581c418f4da 1530552 libsoup3_3.2.3.orig.tar.xz"
  ],
  "Format": [
    "3.0 (quilt)"
  ],
  "Git-Tag-Info": [
    "tag=fa847d591345c7074c0ccb2bad8f16dcde18d15a fp=7a073ad1ae694fa25bff62e5235c099d3eb33076"
  ],
  "Git-Tag-Tagger": [
    "Simon McVittie \u003csmcv@debian.org\u003e"
  ],
  "Homepage": [
    "https://wiki.gnome.org/Projects/libsoup"
  ],
  "Maintainer": [
    "Debian GNOME Maintainers \u003cpkg-gnome-maintainers@lists.alioth.debian.org\u003e"
  ],
  "Package": [
    "libsoup3"
  ],
  "Package-List": [
    "gir1.2-soup-3.0 deb introspection optional arch=any libsoup-3.0-0 deb libs optional arch=any libsoup-3.0-common deb devel optional arch=all libsoup-3.0-dev deb libdevel optional arch=any libsoup-3.0-doc deb doc optional arch=all libsoup-3.0-tests deb misc optional arch=any profile=!noinsttest"
  ],
  "Standards-Version": [
    "4.6.0"
  ],
  "Testsuite": [
    "autopkgtest"
  ],
  "Testsuite-Triggers": [
    "build-essential, dbus, gnome-desktop-testing, winbind, xauth, xvfb"
  ],
  "Uploaders": [
    "Jeremy Bicha \u003cjbicha@ubuntu.com\u003e"
  ],
  "Vcs-Browser": [
    "https://salsa.debian.org/gnome-team/libsoup3/tree/debian/bookworm"
  ],
  "Vcs-Git": [
    "https://salsa.debian.org/gnome-team/libsoup3.git -b debian/bookworm"
  ],
  "Version": [
    "3.2.3-0+deb12u2"
  ]
}