{
  "Architecture": [
    "any all"
  ],
  "Binary": [
    "espeak-ng, espeak-ng-espeak, espeak-ng-data, espeak-ng-data-udeb, libespeak-ng1, libespeak-ng-libespeak1, libespeak-ng-dev, libespeak-ng-libespeak-dev"
  ],
  "Build-Depends": [
    "debhelper-compat (= 13), dh-exec, libpcaudio-dev, libsonic-dev, ronn, kramdown"
  ],
  "Checksums-Sha1": [
    "bf7ee0b16faf24b58ef2614975a987b2e750de83 50664 espeak-ng_1.51+dfsg-10+deb12u2.debian.tar.xz cd999a53bf467aab3518f482defd2f32411c3016 2631 espeak-ng_1.51+dfsg-10+deb12u2.dsc 89f6ac8f1ff45b5b506c612fd3b2dadb1a247535 12985129 espeak-ng_1.51+dfsg.orig.tar.gz"
  ],
  "Checksums-Sha256": [
    "7b8155d1d735ed4eb493945f7bec24895a4f70f96eade430f138bf1af7821210 50664 espeak-ng_1.51+dfsg-10+deb12u2.debian.tar.xz fed64140ddff37b47e5709508884f1f51a1b721550d5785e91c2aad46c237e86 2631 espeak-ng_1.51+dfsg-10+deb12u2.dsc 72242d7c06a4d80f5056335977c5be1ff79ff27bb502d4d054be1803ff787fa9 12985129 espeak-ng_1.51+dfsg.orig.tar.gz"
  ],
  "Checksums-Sha512": [
    "b628bf4c0a04c08e447d080918d570c1b2b9a3efaba7a6c80e3d9c38d99bff0fc9ab324ff162b61c828b37c7954eb2356c9f54a4399acc19b8b857c02d990887 50664 espeak-ng_1.51+dfsg-10+deb12u2.debian.tar.xz 82ae1920ec5d8267825b6a6141cdddbae9a159d59d0748dbf6e9c342637f3ff1cadee4e0f7a5d80b57e75ac087daeac5e2a458c6f1d728ae949fc18b23744fa0 2631 espeak-ng_1.51+dfsg-10+deb12u2.dsc 8dc781a76c229b912b0c9718fc2e960d17457a14ac3b37e3310b9d0076493e71a8ed3d71072e8445e2b44446acec962a741c054cf3170628a79b68b3652127d9 12985129 espeak-ng_1.51+dfsg.orig.tar.gz"
  ],
  "Directory": [
    "pool/main/e/espeak-ng"
  ],
  "Files": [
    "b8442625f280c2989973d27ef01bc356 50664 espeak-ng_1.51+dfsg-10+deb12u2.debian.tar.xz 6bd6694d5a77f5693ebd75b9b6bdf5f8 2631 espeak-ng_1.51+dfsg-10+deb12u2.dsc 69646ee9d1198e4ad4d8b1622c8f15dc 12985129 espeak-ng_1.51+dfsg.orig.tar.gz"
  ],
  "Format": [
    "3.0 (quilt)"
  ],
  "Homepage": [
    "https://github.com/espeak-ng/espeak-ng"
  ],
  "Maintainer": [
    "Debian Accessibility Team \u003cpkg-a11y-devel@alioth-lists.debian.net\u003e"
  ],
  "Package": [
    "espeak-ng"
  ],
  "Package-List": [
    "espeak-ng deb sound optional arch=any espeak-ng-data deb sound optional arch=any espeak-ng-data-udeb udeb debian-installer optional arch=any espeak-ng-espeak deb sound optional arch=all libespeak-ng-dev deb libdevel optional arch=any libespeak-ng-libespeak-dev deb libdevel optional arch=any libespeak-ng-libespeak1 deb libs optional arch=any libespeak-ng1 deb libs optional arch=any"
  ],
  "Standards-Version": [
    "4.6.0"
  ],
  "Testsuite": [
    "autopkgtest"
  ],
  "Testsuite-Triggers": [
    "@builddeps@, clang, libclang-rt-dev"
  ],
  "Uploaders": [
    "Samuel Thibault \u003csthibault@debian.org\u003e"
  ],
  "Vcs-Browser": [
    "https://salsa.debian.org/a11y-team/espeak-ng"
  ],
  "Vcs-Git": [
    "https://salsa.debian.org/a11y-team/espeak-ng.git"
  ],
  "Version": [
    "1.51+dfsg-10+deb12u2"
  ]
}