{
  "Architecture": [
    "linux-any"
  ],
  "Binary": [
    "gnome-initial-setup"
  ],
  "Build-Depends": [
    "debhelper-compat (= 13), dh-sequence-gnome, gsettings-desktop-schemas-dev (\u003e= 3.37.1), itstool, libaccountsservice-dev, libadwaita-1-dev (\u003e= 1.2~alpha), libfontconfig-dev, libgdm-dev (\u003e= 3.8.3), libgeoclue-2-dev (\u003e= 2.3.1), libgeocode-glib-dev, libglib2.0-dev (\u003e= 2.63.1), libgnome-desktop-4-dev, libgoa-1.0-dev (\u003e= 3.45.1), libgoa-backend-1.0-dev (\u003e= 3.45.1), libgtk-4-dev, libgweather-4-dev (\u003e= 4.1), libibus-1.0-dev (\u003e= 1.5.2), libjson-glib-dev, libkrb5-dev, libmalcontent-0-dev [amd64 arm64 armel armhf i386 mipsel mips64el ppc64el s390x hppa hurd-i386 ppc64 riscv64], libmalcontent-ui-dev [amd64 arm64 armel armhf i386 mipsel mips64el ppc64el s390x hppa hurd-i386 ppc64 riscv64], libnm-dev (\u003e= 1.2), libnma-gtk4-dev (\u003e= 1.0), libpango1.0-dev (\u003e= 1.32.5), libpolkit-gobject-1-dev (\u003e= 0.103), libpwquality-dev, librest-dev (\u003e= 0.9.1), libsecret-1-dev (\u003e= 0.18.8), libsystemd-dev [linux-any], libwebkitgtk-6.0-dev, libxml2-utils, meson (\u003e= 0.50.0), systemd (\u003e= 242)"
  ],
  "Checksums-Sha1": [
    "913c478fd4eb57f6817bd0bb96687bafad0687b7 14692 gnome-initial-setup_43.2-6.debian.tar.xz a5a07ffd3da71c21abac1875c7c9dc09b041a4d0 3125 gnome-initial-setup_43.2-6.dsc ea03a02b9605983fe886d1b74d382b9d9c0df15b 528892 gnome-initial-setup_43.2.orig.tar.xz"
  ],
  "Checksums-Sha256": [
    "fdb3abf7617831521f5ef6fd9fade1e362b267325b13a581611dc5e425bd44a2 14692 gnome-initial-setup_43.2-6.debian.tar.xz deb8b17bb6f83916cac81053aa5cc53c00163b49d9b418f5d209e729660d24ef 3125 gnome-initial-setup_43.2-6.dsc 23d7963a54d49594504d0eacd85096cafb5f86f1e74a58e040675b6e798ae698 528892 gnome-initial-setup_43.2.orig.tar.xz"
  ],
  "Checksums-Sha512": [
    "75bee10e94d021c078bd979c4f5806ce0a67feb844bffd6f357bfe3b6038b0e59fc067f36f9c7e8b7e455df375180131facc557eff66faf520ef5dc5c539013a 14692 gnome-initial-setup_43.2-6.debian.tar.xz d174b195947d2859273597ea68788c356412ad8482090a78d00a089cec6f9df5cc1803871de9ed464ac82ef686fbcc0310e2baefe46f257fdfa82f0aee176eb8 3125 gnome-initial-setup_43.2-6.dsc 2ebb2e93fa7f05689eabb0d3684e2fc1b6e4e364c5f6ea26284d5eb57ed0817c1beab317e0389a9a1b2efeddfa9e1c4e5bbdbf5731b5a26b59843ae5f81a00bc 528892 gnome-initial-setup_43.2.orig.tar.xz"
  ],
  "Dgit": [
    "56116de936f6aff4a9ea78bbf41615c57ebe966f debian archive/debian/43.2-6 https://git.dgit.debian.org/gnome-initial-setup"
  ],
  "Directory": [
    "pool/main/g/gnome-initial-setup"
  ],
  "Files": [
    "17b8ac895cb7c3e1672e84f8df21e37a 14692 gnome-initial-setup_43.2-6.debian.tar.xz 82d4434bdc2ac759f54c331a81db5288 3125 gnome-initial-setup_43.2-6.dsc a330915bbf39258091e1bbc664666ca7 528892 gnome-initial-setup_43.2.orig.tar.xz"
  ],
  "Format": [
    "3.0 (quilt)"
  ],
  "Homepage": [
    "https://git.gnome.org/browse/gnome-initial-setup/"
  ],
  "Maintainer": [
    "Debian GNOME Maintainers \u003cpkg-gnome-maintainers@lists.alioth.debian.org\u003e"
  ],
  "Package": [
    "gnome-initial-setup"
  ],
  "Package-List": [
    "gnome-initial-setup deb gnome optional arch=linux-any"
  ],
  "Standards-Version": [
    "4.6.1"
  ],
  "Uploaders": [
    "Jeremy Bicha \u003cjbicha@ubuntu.com\u003e"
  ],
  "Vcs-Browser": [
    "https://salsa.debian.org/gnome-team/gnome-initial-setup"
  ],
  "Vcs-Git": [
    "https://salsa.debian.org/gnome-team/gnome-initial-setup.git"
  ],
  "Version": [
    "43.2-6"
  ]
}