{
  "Architecture": [
    "any"
  ],
  "Binary": [
    "draco, libdraco7, libdraco-dev"
  ],
  "Build-Depends": [
    "cmake, debhelper-compat (= 13), googletest, libeigen3-dev (\u003e= 3.4), libstb-dev, libtinygltf-dev, nlohmann-json3-dev"
  ],
  "Checksums-Sha1": [
    "30f0bc977ebe8bdddad175aa46b396af24a9b166 11916 draco_1.5.5+dfsg-2.debian.tar.xz 5ae281918c21109ec214b693f876d5bb6d91125a 2746 draco_1.5.5+dfsg-2.dsc 93571587ff2c978894404b910246dd1570a17862 37233640 draco_1.5.5+dfsg.orig.tar.xz"
  ],
  "Checksums-Sha256": [
    "f1703de31f3574ff552f0d01123a9a7e94bd5e21f4fa6d78934dd12062d6612d 11916 draco_1.5.5+dfsg-2.debian.tar.xz 169bca5d8f1e8886266ddad8c2415ab7a7ce10c8ed01607b64ced44a20610a87 2746 draco_1.5.5+dfsg-2.dsc 0d4ff5b218a2f9d836c6f44202918402591407b5f59a5103ec288c5600ab087f 37233640 draco_1.5.5+dfsg.orig.tar.xz"
  ],
  "Checksums-Sha512": [
    "384e6a7042c54d7b3d11812720f34bf8c6e5feeaa178203e9445784426a0acadd189cdc95ad454e2de2ea5492bab98087f470bd1553870348265e6e33a6ab750 11916 draco_1.5.5+dfsg-2.debian.tar.xz a8c642a613ce1a0df1598537ba8bc43fd5db4a34cc60ff75f46cef13cc7b534c898003423a4d64a317200eb057dd332d425cec91c1dad73d054741c57c99548c 2746 draco_1.5.5+dfsg-2.dsc e401bba99835f8c335f07dcd7d7f1a42ba02f2e3c94f6d3a36aa763e0528731e36cc40f8dcf4efd6756e0f6531bdb3985cf6f26b14142d8b0345ea2f98706f99 37233640 draco_1.5.5+dfsg.orig.tar.xz"
  ],
  "Description": [
    "Library for compressing 3D geometric meshes and point clouds Draco is a library for compressing and decompressing 3D geometric meshes and point clouds. It is intended to improve the storage and transmission of 3D graphics. . Draco is designed and built for compression efficiency and speed. The code supports compressing points, connectivity information, texture coordinates, color information, normals, and any other generic attributes associated with geometry. With Draco, applications using 3D graphics can be significantly smaller without compromising visual fidelity. For users, this means apps can now be downloaded faster, 3D graphics in the browser can load quicker, and VR and AR scenes can now be transmitted with a fraction of the bandwidth and rendered quickly."
  ],
  "Directory": [
    "pool/main/d/draco"
  ],
  "Files": [
    "33667f4f994de0be2103ad0c1723d005 11916 draco_1.5.5+dfsg-2.debian.tar.xz ac2726319efdba614be2ca7415986f49 2746 draco_1.5.5+dfsg-2.dsc d90420248d5c748715687571e2d2419a 37233640 draco_1.5.5+dfsg.orig.tar.xz"
  ],
  "Format": [
    "3.0 (quilt)"
  ],
  "Homepage": [
    "https://github.com/google/draco"
  ],
  "Maintainer": [
    "Timo Röhling \u003croehling@debian.org\u003e"
  ],
  "Package": [
    "draco"
  ],
  "Package-List": [
    "draco deb graphics optional arch=any libdraco-dev deb libdevel optional arch=any libdraco7 deb libs optional arch=any"
  ],
  "Standards-Version": [
    "4.6.1"
  ],
  "Testsuite": [
    "autopkgtest"
  ],
  "Testsuite-Triggers": [
    "cmake, g++"
  ],
  "Vcs-Browser": [
    "https://salsa.debian.org/roehling/draco"
  ],
  "Vcs-Git": [
    "https://salsa.debian.org/roehling/draco.git"
  ],
  "Version": [
    "1.5.5+dfsg-2"
  ]
}